{"cameraMode":{"drawMode":0,"name":"Shaded","section":"Shading Mode"},"sceneLighting":true,"audioPlay":false,"sceneViewState":{"m_AlwaysRefresh":false,"showFog":true,"showSkybox":true,"showFlares":true,"showImageEffects":true,"showParticleSystems":true,"showVisualEffectGraphs":true,"m_FxEnabled":true},"in2DMode":false,"pivot":{"x":-99.92800903320313,"y":267.82879638671877,"z":-1229.812255859375},"rotation":{"x":-0.012545015662908554,"y":-0.9873056411743164,"z":-0.10224360227584839,"w":0.12115399539470673},"size":643.8380737304688,"orthographic":false}